weightedstats/__init__.py
weightedstats-0.4.1.dist-info/LICENSE.txt
weightedstats-0.4.1.dist-info/METADATA
weightedstats-0.4.1.dist-info/WHEEL
weightedstats-0.4.1.dist-info/top_level.txt
weightedstats-0.4.1.dist-info/RECORD
