Metadata-Version: 2.1
Name: weightedstats
Version: 0.4.1
Summary: Mean, weighted mean, median, weighted median
Home-page: https://github.com/tinybike/weightedstats
Author: Jack Peterson
Author-email: <jack@tinybike.net>
Maintainer: Jack Peterson
Maintainer-email: <jack@tinybike.net>
License: MIT
Download-URL: https://github.com/tinybike/weightedstats/tarball/0.4.1
Keywords: weights,mean,median,numpy,statistics
Platform: UNKNOWN
